JesseLOTRsdk/__init__.py
JesseLOTRsdk/sdk.py
JesseLOTRsdk/tests.py
JesseLOTRsdk/models/__init__.py
JesseLOTRsdk/models/movie.py
JesseLOTRsdk/models/quote.py
JesseLOTRsdk-1.0.0.dist-info/LICENSE.md
JesseLOTRsdk-1.0.0.dist-info/METADATA
JesseLOTRsdk-1.0.0.dist-info/WHEEL
JesseLOTRsdk-1.0.0.dist-info/top_level.txt
JesseLOTRsdk-1.0.0.dist-info/RECORD
