Metadata-Version: 2.1
Name: JesseLOTRsdk
Version: 1.0.0
Summary: An SDK for the Lord of the Rings API. Created for a coding challenge.
Home-page: https://github.com/vincjess
Author: Jesse Vincent
Author-email: vincenjes@gmail.com
Classifier: Programming Language :: Python :: 3
Classifier: License :: OSI Approved :: MIT License
Classifier: Operating System :: OS Independent
Requires-Python: >=3.9
License-File: LICENSE.md
Requires-Dist: python-dotenv
Requires-Dist: requests
